<?xml version="1.0" encoding="UTF-8"?>
<databaseChangeLog xmlns:xsi="http://www.w3.org/2001/XMLSchema-instance" xmlns="http://www.liquibase.org/xml/ns/dbchangelog"
                   xsi:schemaLocation="http://www.liquibase.org/xml/ns/dbchangelog http://www.liquibase.org/xml/ns/dbchangelog/dbchangelog-3.3.xsd">

    <changeSet author="gavink" id="2019-10-18-12-34-29-499-1">
        <insert tableName="USERS" schemaName="ALERT">
            <column name="id" value="2"/>
            <column name="USERNAME" value="jobmanager"/>
            <column name="PASSWORD" value="$2a$16$Ek6E2PbHCTLrlsqSPuNsxexjcViC3n1Gl6AW2sl/yR3Vf52xTazui"/>
            <column name="ENABLED" value="false"/>
        </insert>
        <insert tableName="USERS" schemaName="ALERT">
            <column name="id" value="3"/>
            <column name="USERNAME" value="alertuser"/>
            <column name="PASSWORD" value="$2a$16$Ek6E2PbHCTLrlsqSPuNsxexjcViC3n1Gl6AW2sl/yR3Vf52xTazui"/>
            <column name="ENABLED" value="false"/>
        </insert>
    </changeSet>
    <changeSet author="gavink" id="2019-10-18-12-34-29-499-2">
        <insert tableName="USER_ROLES" schemaName="ALERT">
            <column name="USER_ID" value="2"/>
            <column name="ROLE_ID" value="2"/>
        </insert>
        <insert tableName="USER_ROLES" schemaName="ALERT">
            <column name="USER_ID" value="3"/>
            <column name="ROLE_ID" value="3"/>
        </insert>
    </changeSet>
</databaseChangeLog>
